whatsapptojson/__init__.py
whatsapptojson/constants.py
whatsapptojson/helper.py
whatsapptojson/whatsapptojson.py
whatsapptojson-1.0.dist-info/LICENSE
whatsapptojson-1.0.dist-info/METADATA
whatsapptojson-1.0.dist-info/WHEEL
whatsapptojson-1.0.dist-info/top_level.txt
whatsapptojson-1.0.dist-info/RECORD
