Metadata-Version: 2.1
Name: whatsapptojson
Version: 1.0
Summary: Converts Whatsapp chat files to dictionary or save it in JSON format.
Home-page: https://github.com/ankschoubey/whatsapptojson
Author: Ankush Choubey
Author-email: ankushchoubey@outlook.com
License: UNKNOWN
Platform: UNKNOWN
Classifier: Programming Language :: Python :: 3
Classifier: License :: OSI Approved :: MIT License
Classifier: Operating System :: OS Independent
